fam/__init__.py
fam/blud.py
fam/constants.py
fam/exceptions.py
fam/fam_json.py
fam/fields.py
fam/mapper.py
fam/acl/__init__.py
fam/acl/requirement.py
fam/acl/writer.py
fam/database/__init__.py
fam/database/base.py
fam/database/base_adapter.py
fam/database/couchbase_server.py
fam/database/couchdb.py
fam/database/couchdb_adapter.py
fam/database/custom_token.py
fam/database/firestore.py
fam/database/firestore_adapter.py
fam/database/firestore_contexts.py
fam/database/firestore_test_client.py
fam/database/firestore_test_wrapper.py
fam/database/null.py
fam/database/sync_gateway.py
fam/extra_types/__init__.py
fam/extra_types/lat_long.py
fam/firestore_sync/__init__.py
fam/firestore_sync/syncer.py
fam/schema/__init__.py
fam/schema/mutator.py
fam/schema/validator.py
fam/schema/writer.py
fam/tests/__init__.py
fam/tests/common/__init__.py
fam/tests/common/anything_tests.py
fam/tests/common/basic_tests.py
fam/tests/common/callback_tests.py
fam/tests/common/field_attribute_tests.py
fam/tests/common/index_tests.py
fam/tests/common/migration_tests.py
fam/tests/common/schema_tests.py
fam/tests/depricated/couchbase/couchbase_utils_tests.py
fam/tests/depricated/test_couchbase/__init__.py
fam/tests/depricated/test_couchbase/_test_basic.py
fam/tests/depricated/test_couchbase/_test_basic2.py
fam/tests/depricated/test_couchbase/couchbase_tests.py
fam/tests/depricated/test_sync_gateway/__init__.py
fam/tests/depricated/test_sync_gateway/_test_acl.py
fam/tests/depricated/test_sync_gateway/_test_basic.py
fam/tests/depricated/test_sync_gateway/_test_sync_gateway_common.py
fam/tests/depricated/test_sync_gateway/_test_user.py
fam/tests/depricated/test_sync_gateway/_test_view_creation.py
fam/tests/depricated/test_sync_gateway/config.py
fam/tests/models/__init__.py
fam/tests/models/_test02.py
fam/tests/models/_test03.py
fam/tests/models/acl.py
fam/tests/models/test01.py
fam/tests/models/test04.py
fam/tests/models/test05.py
fam/tests/test_couchdb/__init__.py
fam/tests/test_couchdb/config.py
fam-4.0.1.dist-info/licenses/LICENSE
fam-4.0.1.dist-info/METADATA
fam-4.0.1.dist-info/WHEEL
fam-4.0.1.dist-info/top_level.txt
fam-4.0.1.dist-info/RECORD
