Metadata-Version: 2.4
Name: fam
Version: 4.0.1
Summary: Simple Python ORM for CouchDB, Firebase and Sync Gateway
Home-page: https://github.com/paulharter/fam
Author: Paul Harter
Author-email: paul@glowinthedark.co.uk
License: LICENSE
Classifier: Development Status :: 4 - Beta
Classifier: Natural Language :: English
Classifier: Operating System :: OS Independent
Classifier: Programming Language :: Python :: 3.13
Classifier: License :: OSI Approved :: MIT License
License-File: LICENSE
Requires-Dist: requests
Requires-Dist: simplejson
Requires-Dist: jsonschema
Requires-Dist: mock
Requires-Dist: pytz
Requires-Dist: firebase_admin
Requires-Dist: grpcio
Dynamic: author
Dynamic: author-email
Dynamic: classifier
Dynamic: home-page
Dynamic: license
Dynamic: license-file
Dynamic: requires-dist
Dynamic: summary
